README.md
setup.cfg
setup.py
src/flask_dtable/__init__.py
src/flask_dtable/app.py
src/flask_dtable.egg-info/PKG-INFO
src/flask_dtable.egg-info/SOURCES.txt
src/flask_dtable.egg-info/dependency_links.txt
src/flask_dtable.egg-info/requires.txt
src/flask_dtable.egg-info/top_level.txt