Metadata-Version: 2.1
Name: flask-dtable
Version: 1.0.0
Summary: A simple framework for building HTML Tables for Flask
Home-page: https://github.com/Flory-1/flask_dtable
Author: Florian Lämmlein
Author-email: florian.leammlein@gmail.com
License: UNKNOWN
Download-URL: https://github.com/Flory-1/flask_dtable/archive/v_100.tar.gz
Platform: UNKNOWN
Classifier: Development Status :: 5 - Production/Stable
Classifier: Intended Audience :: Developers
Classifier: Programming Language :: Python
Classifier: License :: OSI Approved :: MIT License
Classifier: Operating System :: OS Independent
Requires-Python: >=3.6
